CG23016UNO/__init__.py
CG23016UNO/lineales.py
CG23016UNO/no_lineales.py
cg23016uno-0.1.6.dist-info/METADATA
cg23016uno-0.1.6.dist-info/WHEEL
cg23016uno-0.1.6.dist-info/top_level.txt
cg23016uno-0.1.6.dist-info/RECORD
