Metadata-Version: 2.4
Name: CG23016UNO
Version: 0.1.6
Summary: Libreria para resolver ecuaciones lineales y no lineales
Author-email: Angel Cardoza <cg23016@ues.edu.sv>
License: MIT
Requires-Python: >=3.7
Requires-Dist: numpy
Requires-Dist: scipy
